<?xml version="1.0" ?>
<?xml-stylesheet type="text/xsl" href="default.xsl"?>
<page title="Screenshots of Version 0.0">
  <screenshot-menu/>

  <screenshots>
    <item file="screen_0.0.14">some more gfx from Joel Fauche and a trap by Michael Mestre, first apearance of the spotmap</item>

    <item file="screen_0.0.13">split screen and scrolling was now possible</item>
    <item file="screen_0.0.12"/>
    <item file="screen_0.0.10">first shoot with Joel Fauche's new Pingu sprites</item>

    <item file="screen_0.0.9">action buttons started to appear</item>

    <item file="screen_0.0.8">after Pingus got ported to ClanLib it also got larger sprites</item>
    
    <item file="screen_0.0.0">the first Pingus screen shot ever! It was for DOS game and used Allegro</item>

  </screenshots>

</page>
